{
  "fecha": "2026-07-15",
  "senales_hoy": 1,
  "historial": [
    {
      "tipo": "entrada",
      "momento": "2026-07-15T06:17:01+00:00",
      "direccion": "venta",
      "entrada": 4032.7,
      "stop": 4042.81,
      "mensaje": "[VENTA] XAU/USD @ 4032.70 | SL 4042.81 | TP 4022.59 (1.0R) / 4012.48 (2.0R) / 4002.38 (3.0R) | P≈64% conf 84% | R:R 1.70",
      "prob": 0.64
    }
  ],
  "abiertas": [
    {
      "direccion": "venta",
      "entrada": 4032.699951171875,
      "riesgo": 10.108021872440986,
      "stop_actual": 4042.807973044316,
      "en_breakeven": false,
      "restante": 1.0,
      "r_acumulado": 0.0,
      "estado": "abierta",
      "abierta_en": "2026-07-15T06:17:01+00:00",
      "resumen": "[VENTA] XAU/USD @ 4032.70 | SL 4042.81 | TP 4022.59 (1.0R) / 4012.48 (2.0R) / 4002.38 (3.0R) | P≈64% conf 84% | R:R 1.70",
      "niveles": [
        [
          4022.591929299434,
          0.5,
          1.0,
          false
        ],
        [
          4012.483907426993,
          0.3,
          2.0,
          false
        ],
        [
          4002.375885554552,
          0.2,
          3.0,
          false
        ]
      ]
    }
  ]
}